Workbook

Sheet DATA
A1: Transaction_ID | B1: Date | C1: Year | D1: Month | E1: Month_Name | F1: Quarter | G1: Region | H1: Department | I1: Product | J1: Units_Sold | K1: Average_Price | L1: Revenue | M1: COGS | N1: Salaries | O1: Marketing_Expense | P1: Rent | Q1: Utilities | R1: Operations_Expense | S1: Other_Expenses | T1: Total_Expenses | U1: Gross_Profit | V1: Operating_Profit | W1: Net_Profit | X1: Budget_Revenue | Y1: Budget_Expenses
A2: TXN-03375 | B2: 44927 | C2: 2023 | D2: 1 | E2: Jan | F2: Q1 | G2: South | H2: Marketing | I2: Product F | J2: 63 | K2: 1739.46 | L2: 109586.18 | M2: 58752.96 | N2: 10416.33 | O2: 3382.2 | P2: 2730.37 | Q2: 1422.72 | R2: 6518.24 | S2: 2389.98 | T2: 85612.8 | U2: 50833.22 | V2: 23973.38 | W2: 23400.91 | X2: 119686.56 | Y2: 87198.64
A3: TXN-03102 | B3: 44927 | C3: 2023 | D3: 1 | E3: Jan | F3: Q1 | G3: South | H3: Sales | I3: Product D | J3: 64 | K3: 1767.28 | L3: 113105.62 | M3: 75637.35 | N3: 12027.73 | O3: 6100.07 | P3: 2090.42 | Q3: 633.45 | R3: 6722 | S3: 1327.12 | T3: 104538.14 | U3: 37468.27 | V3: 8567.47 | W3: 8556.79 | X3: 114402.28 | Y3: 103107.52
A4: TXN-02925 | B4: 44927 | C4: 2023 | D4: 1 | E4: Jan | F4: Q1 | G4: East | H4: Operations | I4: Product H | J4: 40 | K4: 1661.61 | L4: 66464.41 | M4: 39940.78 | N4: 4955.71 | O4: 2415.12 | P4: 1270.78 | Q4: 1049.87 | R4: 2594.67 | S4: 925.15 | T4: 53152.08 | U4: 26523.63 | V4: 13312.33 | W4: 13201.49 | X4: 71411.6 | Y4: 52546.2
A5: TXN-00938 | B5: 44927 | C5: 2023 | D5: 1 | E5: Jan | F5: Q1 | G5: South | H5: Operations | I5: Product G | J5: 50 | K5: 986.3 | L5: 49315.16 | M5: 27491.85 | N5: 3732.35 | O5: 1653.53 | P5: 2026.45 | Q5: 584.33 | R5: 1935.25 | S5: 409.37 | T5: 37833.13 | U5: 21823.31 | V5: 11482.03 | W5: 11272.58 | X5: 51930.87 | Y5: 36749.87
A6: TXN-00720 | B6: 44927 | C6: 2023 | D6: 1 | E6: Jan | F6: Q1 | G6: South | H6: Sales | I6: Product F | J6: 79 | K6: 1790.65 | L6: 141461.7 | M6: 87700.42 | N6: 14555.85 | O6: 7740.21 | P6: 6085.48 | Q6: 1681.94 | R6: 4156.84 | S6: 2163.48 | T6: 124084.22 | U6: 53761.28 | V6: 17377.48 | W6: 17413.76 | X6: 152664.8 | Y6: 130595.98
A7: TXN-01848 | B7: 44928 | C7: 2023 | D7: 1 | E7: Jan | F7: Q1 | G7: South | H7: Sales | I7: Product D | J7: 94 | K7: 1059.44 | L7: 99587.34 | M7: 58454.85 | N7: 8885.38 | O7: 4222.05 | P7: 1597.07 | Q7: 1218.19 | R7: 5121.82 | S7: 1523.63 | T7: 81022.99 | U7: 41132.48 | V7: 18564.35 | W7: 17384.82 | X7: 109652.5 | Y7: 78402.76
A8: TXN-00186 | B8: 44928 | C8: 2023 | D8: 1 | E8: Jan | F8: Q1 | G8: South | H8: Sales | I8: Product H | J8: 82 | K8: 994.98 | L8: 81588.23 | M8: 50598.65 | N8: 7641.34 | O8: 2361.01 | P8: 2314.56 | Q8: 1070.68 | R8: 4838.38 | S8: 1203.96 | T8: 70028.58 | U8: 30989.59 | V8: 11559.66 | W8: 11215.4 | X8: 86644.38 | Y8: 76059.43
A9: TXN-00237 | B9: 44928 | C9: 2023 | D9: 1 | E9: Jan | F9: Q1 | G9: North | H9: Sales | I9: Product A | J9: 26 | K9: 1450.25 | L9: 37706.53 | M9: 22052.66 | N9: 3161.36 | O9: 1404.2 | P9: 742.31 | Q9: 461.99 | R9: 2000.45 | S9: 593.14 | T9: 30416.11 | U9: 15653.87 | V9: 7290.42 | W9: 7265.28 | X9: 35220.56 | Y9: 30772.04
A10: TXN-02068 | B10: 44928 | C10: 2023 | D10: 1 | E10: Jan | F10: Q1 | G10: South | H10: Sales | I10: Product A | J10: 52 | K10: 1215.44 | L10: 63202.93 | M10: 42648.14 | N10: 6491.93 | O10: 4024.91 | P10: 1127.72 | Q10: 417 | R10: 3437.02 | S10: 1238.27 | T10: 59384.99 | U10: 20554.78 | V10: 3817.93 | W10: 3850.24 | X10: 67285.32 | Y10: 60397.34
A11: TXN-01731 | B11: 44928 | C11: 2023 | D11: 1 | E11: Jan | F11: Q1 | G11: East | H11: Sales | I11: Product F | J11: 119 | K11: 905.04 | L11: 107700.26 | M11: 55495.95 | N11: 11690.61 | O11: 3266.17 | P11: 3497.76 | Q11: 1016.11 | R11: 3013.74 | S11: 1544.6 | T11: 79524.93 | U11: 52204.3 | V11: 28175.33 | W11: 28723.54 | X11: 111173.14 | Y11: 87337.38
A12: TXN-01436 | B12: 44929 | C12: 2023 | D12: 1 | E12: Jan | F12: Q1 | G12: South | H12: Sales | I12: Product H | J12: 78 | K12: 1273.01 | L12: 99295.07 | M12: 54101.08 | N12: 11889.83 | O12: 3526.02 | P12: 2236.17 | Q12: 906.54 | R12: 4827.39 | S12: 2329.75 | T12: 79816.78 | U12: 45193.99 | V12: 19478.29 | W12: 18806.69 | X12: 107757.84 | Y12: 87636.78
A13: TXN-04392 | B13: 44929 | C13: 2023 | D13: 1 | E13: Jan | F13: Q1 | G13: North | H13: Marketing | I13: Product E | J13: 34 | K13: 1691.56 | L13: 57512.93 | M13: 30117.06 | N13: 4962.88 | O13: 3296.85 | P13: 1742.92 | Q13: 967.07 | R13: 3424.97 | S13: 529.69 | T13: 45041.44 | U13: 27395.87 | V13: 12471.49 | W13: 11671.1 | X13: 62732.23 | Y13: 48037.27
... A5001: TXN-04817 | B5001: 46295 | C5001: 2026 | D5001: 9 | E5001: Sep | F5001: Q3 | G5001: South | H5001: Sales | I5001: Product H | J5001: 49 | K5001: 1418.64 | L5001: 69513.53 | M5001: 38580.68 | N5001: 7184.69 | O5001: 5196.11 | P5001: 1067.8 | Q5001: 789.56 | R5001: 3177.24 | S5001: 1199.98 | T5001: 57196.06 | U5001: 30932.85 | V5001: 12317.47 | W5001: 11606.08 | X5001: 77052.7 | Y5001: 62818.62

Sheet FORECASTING
A1: Month | B1: Revenue | C1: Forecast(Revenue) | D1: Lower Confidence Bound(Revenue) | E1: Upper Confidence Bound(Revenue)
A2: 44927 | B2: 28918543
A3: 44958 | B3: 26208769
A4: 44986 | B4: 26231266
A5: 45017 | B5: 27385296
A6: 45047 | B6: 28644482
A7: 45078 | B7: 27310038
A8: 45108 | B8: 30236778
A9: 45139 | B9: 27966459
A10: 45170 | B10: 25790199
A11: 45200 | B11: 20271633
A12: 45231 | B12: 19016549
A13: 45261 | B13: 21341487 | C13: 21341487 | D13: 21341487 | E13: 21341487
A14: 45292 | C14: =_xlfn.FORECAST.ETS(A14,$B$2:$B$13,$A$2:$A$13,1,1) -> 20723165 | D14: =C14-_xlfn.FORECAST.ETS.CONFINT(A14,$B$2:$B$13,$A$2:$A$13,0.95,1,1) -> 15615867 | E14: =C14+_xlfn.FORECAST.ETS.CONFINT(A14,$B$2:$B$13,$A$2:$A$13,0.95,1,1) -> 25830462
A15: 45323 | C15: =_xlfn.FORECAST.ETS(A15,$B$2:$B$13,$A$2:$A$13,1,1) -> 20042346 | D15: =C15-_xlfn.FORECAST.ETS.CONFINT(A15,$B$2:$B$13,$A$2:$A$13,0.95,1,1) -> 14935026 | E15: =C15+_xlfn.FORECAST.ETS.CONFINT(A15,$B$2:$B$13,$A$2:$A$13,0.95,1,1) -> 25149666
A16: 45352 | C16: =_xlfn.FORECAST.ETS(A16,$B$2:$B$13,$A$2:$A$13,1,1) -> 19361527 | D16: =C16-_xlfn.FORECAST.ETS.CONFINT(A16,$B$2:$B$13,$A$2:$A$13,0.95,1,1) -> 14254166 | E16: =C16+_xlfn.FORECAST.ETS.CONFINT(A16,$B$2:$B$13,$A$2:$A$13,0.95,1,1) -> 24468888

Sheet TABLES
A7: TOTAL BUDGET EXP | C7: REVENUE VARIANCE | E7: EXP VARIANCE | G7: REVENUE ACHIVEMENT | I7: TOTAL EXPENESES
A8: =SUM(DATA!X2:X5001) -> 3.1565063e+08 | C8: =B23-A8 -> -6329128.6 | E8: =SUM(DATA!T2:T5001)-SUM(DATA!X2:X5001) -> -58619070 | G8: =SUM(TABLES!B23)/A8 -> 0.97994894 | I8: =SUM(DATA!T2:T5001) -> 2.5703156e+08
A13: EXPENSE CATEGORY | B13: TOTAL EXP | D13: PROFIT TYPE | E13: AMOUNT | G13: Margin Type | H13: Percentage | K13: Month | L13: Revenue | O13: Month | P13: Revenue
A14: SALARIES | B14: =SUM(DATA!N2:N5001) -> 30923377 | D14: GROSS PROFIT | E14: =SUM(DATA!U2:U5001) -> 1.3049174e+08 | G14: PROFIT MARGIN | H14: =SUM(DATA!W2:W5001)/SUM(DATA!L2:L5001) -> 0.16063352 | K14: Jan | L14: =SUMIFS(Table1[Revenue],Table1[Date],">="&DATE(2026,1,1),Table1[Date],"<"&DATE(2026,2,1)) -> 7609133.6 | O14: =DATE(2023,1,1) -> 44927 | P14: 28918543
A15: MARKETING | B15: =SUM(DATA!O2:O5001) -> 15429596 | D15: OPERATING PRODUCT | E15: =SUM(DATA!V2:V5001) -> 52289941 | G15: GROSS MARGIN | H15: =TABLES!E14/TABLES!B23 -> 0.42186444 | K15: Feb | L15: =SUMIFS(Table1[Revenue],Table1[Date],">="&DATE(2026,2,1),Table1[Date],"<"&DATE(2026,3,1)) -> 7351136.9 | O15: =DATE(2023,2,1) -> 44958 | P15: 26208769
A16: RENT | B16: =SUM(DATA!P2:P5001) -> 9244369.8 | D16: NET PROFIT | E16: =SUM(DATA!W2:W5001) -> 49687400 | G16: OPERATING MARGIN | H16: =SUM(DATA!V2:V5001/DATA!L2:L5001) -> 0.22962073 | K16: Mar | L16: =SUMIFS(Table1[Revenue],Table1[Date],">="&DATE(2026,3,1),Table1[Date],"<"&DATE(2026,4,1)) -> 6856181.7 | O16: =DATE(2023,3,1) -> 44986 | P16: 26231266
A17: UTILITIES | B17: =SUM(DATA!Q2:Q5001) -> 3549790.1 | K17: Apr | L17: =SUMIFS(Table1[Revenue],Table1[Date],">="&DATE(2026,4,1),Table1[Date],"<"&DATE(2026,5,1)) -> 6301426.3 | O17: =DATE(2023,4,1) -> 45017 | P17: 27385296
A18: OPERATION | B18: =SUM(DATA!R2:R5001) -> 13936101 | K18: May | L18: =SUMIFS(Table1[Revenue],Table1[Date],">="&DATE(2026,5,1),Table1[Date],"<"&DATE(2026,6,1)) -> 6925362.8 | O18: =DATE(2023,5,1) -> 45047 | P18: 28644482
A19: OTHER EXP | B19: =SUM(DATA!R2:R5001) -> 13936101 | K19: Jun | L19: =SUMIFS(Table1[Revenue],Table1[Date],">="&DATE(2026,6,1),Table1[Date],"<"&DATE(2026,7,1)) -> 7055909.5 | O19: =DATE(2023,6,1) -> 45078 | P19: 27310038
A20: TOTAL COGS | B20: =SUM(DATA!M2:M5001) -> 1.7882976e+08 | K20: Jul | L20: =SUMIFS(Table1[Revenue],Table1[Date],">="&DATE(2026,7,1),Table1[Date],"<"&DATE(2026,8,1)) -> 7306484.4 | O20: =DATE(2023,7,1) -> 45108 | P20: 30236778
K21: Aug | L21: =SUMIFS(Table1[Revenue],Table1[Date],">="&DATE(2026,8,1),Table1[Date],"<"&DATE(2026,9,1)) -> 7377165.6 | O21: =DATE(2023,8,1) -> 45139 | P21: 27966459
A22: REVENUE TYPE | B22: AMOUNT | D22: Category | E22: Amount | G22: Month | H22: Revenue | K22: Sep | L22: =SUMIFS(Table1[Revenue],Table1[Date],">="&DATE(2026,9,1),Table1[Date],"<"&DATE(2026,10,1)) -> 6177972.3 | O22: =DATE(2023,9,1) -> 45170 | P22: 25790199
A23: TOTAl REVENUE | B23: =SUM(DATA!L2:L5001) -> 3.093215e+08 | D23: Actual Expenses | E23: =SUM(Table1[Total_Expenses]) -> 2.5703156e+08 | G23: Jan | H23: =SUMIF(Table1[Month_Name],TABLES!G23,Table1[Revenue]) -> 28918543 | K23: Oct | L23: =SUMIFS(Table1[Revenue],Table1[Date],">="&DATE(2026,9,1),Table1[Date],"<"&DATE(2026,10,1)) -> 6177972.3 | O23: =DATE(2023,10,1) -> 45200 | P23: 20271633
A24: TOTAL BUDGET REVENUE | B24: =SUM(DATA!Y2:Y5001) -> 2.6097093e+08 | D24: Budget Expenses | E24: =SUM(Table1[Budget_Expenses]) -> 2.6097093e+08 | G24: Feb | H24: =SUMIF(Table1[Month_Name],TABLES!G24,Table1[Revenue]) -> 26208769 | K24: Nov | L24: =SUMIFS(Table1[Revenue],Table1[Date],">="&DATE(2026,9,1),Table1[Date],"<"&DATE(2026,10,1)) -> 6177972.3 | O24: =DATE(2023,11,1) -> 45231 | P24: 19016549
G25: Mar | H25: =SUMIF(Table1[Month_Name],TABLES!G25,Table1[Revenue]) -> 26231266 | K25: Dec | L25: =SUMIFS(Table1[Revenue],Table1[Date],">="&DATE(2026,9,1),Table1[Date],"<"&DATE(2026,10,1)) -> 6177972.3 | O25: =DATE(2023,12,1) -> 45261 | P25: 21341487
G26: Apr | H26: =SUMIF(Table1[Month_Name],TABLES!G26,Table1[Revenue]) -> 27385296
G27: May | H27: =SUMIF(Table1[Month_Name],TABLES!G27,Table1[Revenue]) -> 28644482
G28: Jun | H28: =SUMIF(Table1[Month_Name],TABLES!G28,Table1[Revenue]) -> 27310038
G29: Jul | H29: =SUMIF(Table1[Month_Name],TABLES!G29,Table1[Revenue]) -> 30236778
G30: Aug | H30: =SUMIF(Table1[Month_Name],TABLES!G30,Table1[Revenue]) -> 27966459
G31: Sep | H31: =SUMIF(Table1[Month_Name],TABLES!G31,Table1[Revenue]) -> 25790199
G32: Oct | H32: =SUMIF(Table1[Month_Name],TABLES!G32,Table1[Revenue]) -> 20271633
G33: Nov | H33: =SUMIF(Table1[Month_Name],TABLES!G33,Table1[Revenue]) -> 19016549
G34: Dec | H34: =SUMIF(Table1[Month_Name],TABLES!G34,Table1[Revenue]) -> 21341487

Sheet DASHBOARD
